ADFDeployer/__init__.py
ADFDeployer/deployer.py
ADFDeployer/runner.py
ADFDeployer-1.0.0a2.dist-info/LICENSE
ADFDeployer-1.0.0a2.dist-info/METADATA
ADFDeployer-1.0.0a2.dist-info/WHEEL
ADFDeployer-1.0.0a2.dist-info/entry_points.txt
ADFDeployer-1.0.0a2.dist-info/top_level.txt
ADFDeployer-1.0.0a2.dist-info/RECORD
